<annotation>
	<folder>collectedimages</folder>
	<filename>S.f56659f9-de7d-11eb-9493-18c04d373779.jpg</filename>
	<path>C:\Users\User\Desktop\Deep Learning\RealTimeObjectDetection\Tensorflow\workspace\images\collectedimages\S.f56659f9-de7d-11eb-9493-18c04d373779.jpg</path>
	<source>
		<database>Unknown</database>
	</source>
	<size>
		<width>640</width>
		<height>480</height>
		<depth>3</depth>
	</size>
	<segmented>0</segmented>
	<object>
		<name>S</name>
		<pose>Unspecified</pose>
		<truncated>0</truncated>
		<difficult>0</difficult>
		<bndbox>
			<xmin>66</xmin>
			<ymin>184</ymin>
			<xmax>227</xmax>
			<ymax>345</ymax>
		</bndbox>
	</object>
</annotation>
